espbm/__init__.py
espbm/curlyBrace.py
espbm/eye_state_prototype.py
espbm/manual.py
espbm/match.py
espbm/plot.py
espbm/unsupervised.py
espbm-1.2.2.dist-info/METADATA
espbm-1.2.2.dist-info/WHEEL
espbm-1.2.2.dist-info/top_level.txt
espbm-1.2.2.dist-info/RECORD
