Metadata-Version: 2.4
Name: espbm
Version: 1.2.2
Summary: Eye State Prototype Blink Matching in EAR time series
License: MIT
Platform: any
Requires-Python: >=3.9
Requires-Dist: numpy>=1.23
Requires-Dist: pandas>=2.2
Requires-Dist: scipy<1.13,>=1.12
Requires-Dist: numba>=0.59
Requires-Dist: stumpy>=1.12
Requires-Dist: matplotlib<4,>=3.5
